zipstream/__init__.py
zipstream/compat.py
zipstream-1.1.3.dist-info/DESCRIPTION.rst
zipstream-1.1.3.dist-info/METADATA
zipstream-1.1.3.dist-info/RECORD
zipstream-1.1.3.dist-info/WHEEL
zipstream-1.1.3.dist-info/metadata.json
zipstream-1.1.3.dist-info/pbr.json
zipstream-1.1.3.dist-info/top_level.txt
