Metadata-Version: 2.0
Name: zipstream
Version: 1.1.3
Summary: Zipfile generator
Home-page: https://github.com/allanlei/python-zipstream
Author: Allan Lei
Author-email: allanlei@helveticode.com
License: UNKNOWN
Keywords: zip streaming
Platform: UNKNOWN
